{"id":"2C406840-5EDB-40ED-87DE-71E49623AE72","validationEntity":{"analysedDataType":"auto","dataResult":{"createdDate":"2022-10-19T14:21:48Z"}},"modelEntity":{"createdDate":"2022-10-19T14:21:48Z","id":"CA58340B-2C12-477E-BE04-D4C3CD611F32","experimentID":"2C406840-5EDB-40ED-87DE-71E49623AE72","title":"","modifiedDate":"2022-10-19T14:21:48Z","preferredFilename":"","version":"1.0","modelURL":"Models\/changeFloorClassifier%2028.mlmodel"},"version":"1.0","settingEntity":{"augmentations":[],"suggestedColumns":["acceleration_x","acceleration_y","acceleration_z","differenceAltitude","differencePressure","relativeAltitude","rotationRate_x","rotationRate_y","rotationRate_z"],"seedType":"default","transferLearningEmbeddingType":"dynamic","handPoseClassifierAugmentations":[],"featureNames":["acceleration_x","acceleration_y","acceleration_z","differenceAltitude","differencePressure","rotationRate_x","rotationRate_y","rotationRate_z"],"algorithmType":"maxEnt","harVideoAugmentations":0,"taskType":"activityClassifier","suggestedColumnValues":["-0,11, -0,13, -0,11, -0,07, -0,05…","-0,21, -0,23, -0,17, -0,06, 0,03…","-0,41, -0,46, -0,60, -0,69, -0,67…","0,00, 0,00, 0,00, 0,00, 0,00…","0,00, 0,00, 0,00, 0,00, 0,00…","0,34, 0,34, 0,34, 0,34, 0,34…","-0,09, -0,19, -0,10, 0,28, 0,91…","-0,51, 0,09, 0,41, 0,25, -0,32…","-0,20, -0,26, -0,35, -0,51, -0,74…"],"handActionClassifierAugmentations":[],"suggestedColumnTypes":["Double","Double","Double","Double","Double","Double","Double","Double","Double"],"sampleRate":50,"styleTransferAlgorithmType":"image","predictionWindowSize":150,"iterationCount":40,"batchSize":64},"state":"trained","trainingEntity":{"finishTime":"2022-10-19T14:23:04Z","resumableCheckpointURL":"Checkpoints\/2C406840-5EDB-40ED-87DE-71E49623AE72.changeFloorClassifier28.checkpoint","validationResults":{"activityClassifier":{"confusionMatrix":[{"expected":"elevator_up","actual":"elevator_up","count":367},{"expected":"eleveator_down","actual":"eleveator_down","count":3205},{"expected":"stairs_down","actual":"stairs_down","count":3058},{"expected":"stairs_up","actual":"stairs_up","count":724},{"expected":"stairs_up","actual":"stay","count":1350},{"expected":"stay","actual":"stay","count":1654}],"statsByLabel":{"stairs_up":{"count":724,"precisionRecall":{"success":{"recall":1,"precision":0.34908389585342331}}},"eleveator_down":{"count":3205,"precisionRecall":{"success":{"recall":1,"precision":1}}},"stairs_down":{"count":3058,"precisionRecall":{"success":{"recall":1,"precision":1}}},"elevator_up":{"count":367,"precisionRecall":{"success":{"recall":1,"precision":1}}},"stay":{"count":3004,"precisionRecall":{"success":{"recall":0.55059920106524629,"precision":1}}}},"accuracy":0.86966595867928176}},"dataURL":"file:\/\/\/Users\/marcoincerti\/Desktop\/change-floor-detection-ActivityClassifier-CoreMLModel\/dataML\/train\/","dataResult":{"itemsCount":214,"createdDate":"2022-10-19T14:21:48Z","columns":["acceleration_x","acceleration_y","acceleration_z","differenceAltitude","differencePressure","relativeAltitude","rotationRate_x","rotationRate_y","rotationRate_z"],"dataURL":"file:\/\/\/Users\/marcoincerti\/Desktop\/change-floor-detection-ActivityClassifier-CoreMLModel\/dataML\/train\/","classesCount":5,"dataSourceID":"949E9243-B46F-4436-B0F1-08291EBC4DD4","columnTypes":["Double","Double","Double","Double","Double","Double","Double","Double","Double"],"columnValues":["-0,11, -0,13, -0,11, -0,07, -0,05…","-0,21, -0,23, -0,17, -0,06, 0,03…","-0,41, -0,46, -0,60, -0,69, -0,67…","0,00, 0,00, 0,00, 0,00, 0,00…","0,00, 0,00, 0,00, 0,00, 0,00…","0,34, 0,34, 0,34, 0,34, 0,34…","-0,09, -0,19, -0,10, 0,28, 0,91…","-0,51, 0,09, 0,41, 0,25, -0,32…","-0,20, -0,26, -0,35, -0,51, -0,74…"],"dataAnalysis":{"summary":{"canUseValidation":1,"classCount":5,"sampleCount":214},"issues":[{"description":"5 classes found, including stay, stairs_down, stairs_up","severity":"debug"},{"description":"214 activity recording files found, automatically creating validation set","severity":"good"},{"description":"Smallest class is \"eleveator_down\" with 21 activity recording files","severity":"debug"},{"description":"Largest class is \"stay\" with 65 activity recording files","severity":"debug"},{"description":"8 features are selected","severity":"good"}],"classifierAnalysis":{"labelStats":{"stairs_up":46,"eleveator_down":21,"stairs_down":50,"elevator_up":32,"stay":65}}}},"trainingResults":{"activityClassifier":{"confusionMatrix":[{"expected":"elevator_up","actual":"elevator_up","count":17621},{"expected":"eleveator_down","actual":"eleveator_down","count":9242},{"expected":"stairs_down","actual":"stairs_down","count":18817},{"expected":"stairs_up","actual":"stairs_up","count":25522},{"expected":"stairs_up","actual":"stay","count":750},{"expected":"stay","actual":"stay","count":58359}],"statsByLabel":{"stairs_up":{"count":25522,"precisionRecall":{"success":{"recall":1,"precision":0.97145249695493296}}},"eleveator_down":{"count":9242,"precisionRecall":{"success":{"recall":1,"precision":1}}},"elevator_up":{"count":17621,"precisionRecall":{"success":{"recall":1,"precision":1}}},"stairs_down":{"count":18817,"precisionRecall":{"success":{"recall":1,"precision":1}}},"stay":{"count":59109,"precisionRecall":{"success":{"recall":0.98731157691722071,"precision":1}}}},"accuracy":0.99424453806662527}},"progress":[{"isLast":false,"currentRowIndex":0,"count":1,"tableDone":false,"acColumnHeader":{"hasValidation":true,"elapsedTime":0.88219099999999995,"trainingAccuracy":0.21166287362575531,"iterationCount":1,"validationAccuracy":0.39901524782180786},"tableIndex":0,"percentComplete":0},{"isLast":false,"currentRowIndex":0,"count":2,"tableDone":false,"acColumnHeader":{"hasValidation":true,"elapsedTime":1.503506,"trainingAccuracy":0.4080238938331604,"iterationCount":2,"validationAccuracy":0.50762695074081421},"tableIndex":0,"percentComplete":0},{"isLast":false,"currentRowIndex":0,"count":3,"tableDone":false,"acColumnHeader":{"hasValidation":true,"elapsedTime":1.90584,"trainingAccuracy":0.51946496963500977,"iterationCount":3,"validationAccuracy":0.60590845346450806},"tableIndex":0,"percentComplete":0},{"isLast":false,"currentRowIndex":0,"count":4,"tableDone":false,"acColumnHeader":{"hasValidation":true,"elapsedTime":2.3209810000000002,"trainingAccuracy":0.58569115400314331,"iterationCount":4,"validationAccuracy":0.67590266466140747},"tableIndex":0,"percentComplete":0},{"isLast":false,"currentRowIndex":0,"count":5,"tableDone":false,"acColumnHeader":{"hasValidation":true,"elapsedTime":2.7278029999999998,"trainingAccuracy":0.64072871208190918,"iterationCount":5,"validationAccuracy":0.73189806938171387},"tableIndex":0,"percentComplete":0},{"isLast":false,"currentRowIndex":0,"count":6,"tableDone":false,"acColumnHeader":{"hasValidation":true,"elapsedTime":3.322092,"trainingAccuracy":0.66339755058288574,"iterationCount":6,"validationAccuracy":0.81878739595413208},"tableIndex":0,"percentComplete":0},{"isLast":false,"currentRowIndex":0,"count":11,"tableDone":false,"acColumnHeader":{"hasValidation":true,"elapsedTime":6.490856,"trainingAccuracy":0.8376806378364563,"iterationCount":11,"validationAccuracy":0.99758642911911011},"tableIndex":0,"percentComplete":0},{"isLast":false,"currentRowIndex":0,"count":21,"tableDone":false,"acColumnHeader":{"hasValidation":true,"elapsedTime":11.373036000000001,"trainingAccuracy":0.93942952156066895,"iterationCount":21,"validationAccuracy":0.92759221792221069},"tableIndex":0,"percentComplete":0},{"isLast":false,"currentRowIndex":0,"count":31,"tableDone":false,"acColumnHeader":{"hasValidation":true,"elapsedTime":15.588196,"trainingAccuracy":0.969066321849823,"iterationCount":31,"validationAccuracy":0.86966598033905029},"tableIndex":0,"percentComplete":0},{"isLast":false,"currentRowIndex":0,"count":40,"tableDone":true,"acColumnHeader":{"hasValidation":true,"elapsedTime":19.414617,"trainingAccuracy":0.98837399482727051,"iterationCount":40,"validationAccuracy":0.86966598033905029},"tableIndex":0,"percentComplete":0}],"trainingAccuracy":0.99424453806662527,"checkpointMetrics":{"10":{"metrics":{"loss":0.13836392760276794,"validationLoss":0,"accuracy":0.79547393321990967,"validationAccuracy":0.99758642911911011},"createdDate":"2022-10-19T14:22:49Z","iteration":10},"30":{"metrics":{"loss":0.038305729627609267,"validationLoss":0,"accuracy":0.95862972736358643,"validationAccuracy":0.85518437623977661},"createdDate":"2022-10-19T14:22:58Z","iteration":30},"20":{"metrics":{"loss":0.044993869960308061,"validationLoss":0,"accuracy":0.92457276582717896,"validationAccuracy":0.92759221792221069},"createdDate":"2022-10-19T14:22:54Z","iteration":20},"40":{"metrics":{"loss":0.0099315876141190529,"validationLoss":0,"accuracy":0.98837399482727051,"validationAccuracy":0.86966598033905029},"createdDate":"2022-10-19T14:23:02Z","iteration":40}},"analysedDataType":"datasource","dataSourceID":"949E9243-B46F-4436-B0F1-08291EBC4DD4","snapshottableCheckpoints":{"40":{"modelURL":"file:\/\/\/Users\/marcoincerti\/Library\/Caches\/com.apple.dt.createml\/projects\/531CBE3F-FB94-44F9-B16C-4537B115D90Ac66850596e3981a29a741d787af28ebbafc95bd5\/sessions\/checkpoint.sessions\/2C406840-5EDB-40ED-87DE-71E49623AE72\/training-000000040.checkpoint.model\/checkpointModel.mlmodel","createdDate":"2022-10-19T14:23:02Z","iteration":40}},"resumableCheckpoint":{"checkpointURL":"file:\/\/\/Users\/marcoincerti\/Library\/Caches\/com.apple.dt.createml\/projects\/531CBE3F-FB94-44F9-B16C-4537B115D90Ac66850596e3981a29a741d787af28ebbafc95bd5\/sessions\/checkpoint.sessions\/2C406840-5EDB-40ED-87DE-71E49623AE72\/training-000000040.checkpoint","createdDate":"2022-10-19T14:23:02Z","iteration":40},"featureExtractionCheckpointMayBeAvailable":false,"snapshottableCheckpointModelURL":"Checkpoints\/2C406840-5EDB-40ED-87DE-71E49623AE72.changeFloorClassifier28.checkpoint\/training-000000040.checkpoint.model\/checkpointModel.mlmodel","validationAccuracy":0.86966595867928176,"startTime":"2022-10-19T14:22:22Z"},"createdDate":"2022-10-19T14:21:48Z","evaluationContainerEntity":{"testingEvaluationEntity":{"evaluationResult":{"activityClassifier":{"statsByLabel":{"stay":{"count":91,"precisionRecall":{"success":{"recall":0.86813186813186816,"precision":0.96341463414634143}}},"eleveator_down":{"count":19,"precisionRecall":{"success":{"recall":1,"precision":0.73076923076923073}}},"stairs_down":{"count":50,"precisionRecall":{"success":{"recall":0.80000000000000004,"precision":1}}},"elevator_up":{"count":27,"precisionRecall":{"success":{"recall":1,"precision":1}}},"stairs_up":{"count":38,"precisionRecall":{"success":{"recall":1,"precision":0.76000000000000001}}}},"accuracy":0.90222222222222226}},"createdDate":"2022-10-19T14:21:48Z","id":"d08dddec-c636-4b83-bce6-df5a8018fe48","dataURL":"file:\/\/\/Users\/marcoincerti\/Desktop\/change-floor-detection-ActivityClassifier-CoreMLModel\/dataML\/test\/","dataSourceID":"212503F6-F425-4857-8D2D-541D7C2BFAE1","dataResult":{"itemsCount":44,"createdDate":"2022-10-19T14:21:48Z","columns":["acceleration_x","acceleration_y","acceleration_z","differenceAltitude","differencePressure","relativeAltitude","rotationRate_x","rotationRate_y","rotationRate_z"],"dataURL":"file:\/\/\/Users\/marcoincerti\/Desktop\/change-floor-detection-ActivityClassifier-CoreMLModel\/dataML\/test\/","classesCount":5,"dataSourceID":"212503F6-F425-4857-8D2D-541D7C2BFAE1","columnTypes":["Double","Double","Double","Double","Double","Double","Double","Double","Double"],"columnValues":["-0,03, -0,02, -0,01, 0,01, 0,01…","0,16, 0,16, 0,15, 0,14, 0,12…","0,22, 0,26, 0,29, 0,31, 0,31…","0,00, 0,00, 0,00, 0,00, 0,00…","0,00, 0,00, 0,00, 0,00, 0,00…","0,39, 0,39, 0,39, 0,39, 0,39…","0,47, 0,51, 0,49, 0,43, 0,34…","-0,58, -0,44, -0,31, -0,23, -0,15…","0,25, 0,15, 0,09, 0,07, 0,08…"],"dataAnalysis":{"summary":{"canUseValidation":0,"classCount":5,"sampleCount":44},"issues":[{"description":"5 classes found, including stay, stairs_down, stairs_up","severity":"debug"},{"description":"Less than 100 total activity recording files found - add more to improve model validation","severity":"warning"},{"description":"Smallest class is \"eleveator_down\" with 5 activity recording files","severity":"debug"},{"description":"Largest class is \"stay\" with 12 activity recording files","severity":"debug"},{"description":"8 features are selected","severity":"good"}],"classifierAnalysis":{"labelStats":{"stay":12,"eleveator_down":5,"stairs_down":11,"elevator_up":7,"stairs_up":9}}}},"analysedDataType":"datasource","accuracy":0.90222222222222226,"startTime":"2022-10-19T14:23:06Z","finishTime":"2022-10-19T14:23:15Z"},"createdDate":"2022-10-19T15:51:09Z","id":"baf21604-dea8-4ad4-81fc-18a2aabaf9a1","trainingEvaluationEntity":{"evaluationResult":{"activityClassifier":{"confusionMatrix":[{"expected":"elevator_up","actual":"elevator_up","count":17621},{"expected":"eleveator_down","actual":"eleveator_down","count":9242},{"expected":"stairs_down","actual":"stairs_down","count":18817},{"expected":"stairs_up","actual":"stairs_up","count":25522},{"expected":"stairs_up","actual":"stay","count":750},{"expected":"stay","actual":"stay","count":58359}],"statsByLabel":{"stay":{"count":59109,"precisionRecall":{"success":{"recall":0.98731157691722071,"precision":1}}},"eleveator_down":{"count":9242,"precisionRecall":{"success":{"recall":1,"precision":1}}},"stairs_down":{"count":18817,"precisionRecall":{"success":{"recall":1,"precision":1}}},"elevator_up":{"count":17621,"precisionRecall":{"success":{"recall":1,"precision":1}}},"stairs_up":{"count":25522,"precisionRecall":{"success":{"recall":1,"precision":0.97145249695493296}}}},"accuracy":0.99424453806662527}},"createdDate":"2022-10-19T14:21:48Z","id":"35f99a19-5589-4498-a5db-bab64d4ac401","dataURL":"file:\/\/\/Users\/marcoincerti\/Desktop\/change-floor-detection-ActivityClassifier-CoreMLModel\/dataML\/train\/","dataSourceID":"949E9243-B46F-4436-B0F1-08291EBC4DD4","dataResult":{"itemsCount":214,"createdDate":"2022-10-19T14:21:48Z","dataURL":"file:\/\/\/Users\/marcoincerti\/Desktop\/change-floor-detection-ActivityClassifier-CoreMLModel\/dataML\/train\/","dataSourceID":"949E9243-B46F-4436-B0F1-08291EBC4DD4","classesCount":5,"dataAnalysis":{"summary":{"canUseValidation":1,"classCount":5,"sampleCount":214},"issues":[{"description":"5 classes found, including stay, stairs_down, stairs_up","severity":"debug"},{"description":"214 activity recording files found, automatically creating validation set","severity":"good"},{"description":"Smallest class is \"eleveator_down\" with 21 activity recording files","severity":"debug"},{"description":"Largest class is \"stay\" with 65 activity recording files","severity":"debug"},{"description":"8 features are selected","severity":"good"}],"classifierAnalysis":{"labelStats":{"stairs_up":46,"eleveator_down":21,"elevator_up":32,"stairs_down":50,"stay":65}}}},"analysedDataType":"none"},"previewType":"activityClassifier","modifiedDate":"2022-10-19T15:51:09Z","validationEvaluationEntity":{"id":"9236ec94-5c0c-4493-b6de-d577255884be","createdDate":"2022-10-19T14:21:48Z","dataResult":{"createdDate":"2022-10-19T14:21:48Z"},"analysedDataType":"auto","evaluationResult":{"activityClassifier":{"confusionMatrix":[{"expected":"elevator_up","actual":"elevator_up","count":367},{"expected":"eleveator_down","actual":"eleveator_down","count":3205},{"expected":"stairs_down","actual":"stairs_down","count":3058},{"expected":"stairs_up","actual":"stairs_up","count":724},{"expected":"stairs_up","actual":"stay","count":1350},{"expected":"stay","actual":"stay","count":1654}],"statsByLabel":{"stay":{"count":3004,"precisionRecall":{"success":{"recall":0.55059920106524629,"precision":1}}},"eleveator_down":{"count":3205,"precisionRecall":{"success":{"recall":1,"precision":1}}},"stairs_down":{"count":3058,"precisionRecall":{"success":{"recall":1,"precision":1}}},"elevator_up":{"count":367,"precisionRecall":{"success":{"recall":1,"precision":1}}},"stairs_up":{"count":724,"precisionRecall":{"success":{"recall":1,"precision":0.34908389585342331}}}},"accuracy":0.86966595867928176}}},"evaluationEntities":[]},"activityEntities":["evaluationStarted",[{"id":"1140F7C2-7C75-4B07-B759-BE7E00D60CD0","title":"Testing Started","createdDate":"2022-10-19T14:23:06Z","event":"evaluationStarted","subtitle":"changeFloorClassifier 28"}],"evaluationFinished",[{"id":"5A551D67-E777-49E9-8028-F3255F0B5B67","title":"Testing Completed","createdDate":"2022-10-19T14:23:15Z","event":"evaluationFinished","subtitle":"changeFloorClassifier 28"}],"trainingDataAdded",[{"id":"DE5C8A31-4928-46D7-A79C-0883FE606AB0","title":"Training Data Added","createdDate":"2022-10-19T14:21:52Z","event":"trainingDataAdded","subtitle":"train"}],"trainingStarted",[{"id":"58C05A64-1505-40F9-A3E1-CBEB08E118A7","title":"Training Started","createdDate":"2022-10-19T14:22:22Z","event":"trainingStarted","subtitle":"40 iterations"}],"experimentCreated",[{"id":"22B274E8-8BEE-4912-A160-038EF81395EE","title":"Model Source Created","createdDate":"2022-10-19T14:21:48Z","event":"experimentCreated","subtitle":"changeFloorClassifier 28"}],"trainingFinished",[{"id":"2ED44842-45FC-40AD-82D2-244CB8140895","title":"Training Completed","createdDate":"2022-10-19T14:23:04Z","event":"trainingFinished","subtitle":"40 iterations"}]],"evaluationState":"evaluated","title":"changeFloorClassifier 28","evaluationEntity":{"id":"6e7ebaaf-a20d-40c0-8378-e3db357db2da","analysedDataType":"none","dataResult":{}},"snapshotRole":{"withoutSnapshots":0},"contentDataResult":{"createdDate":"2022-10-19T14:21:48Z"},"modifiedDate":"2022-10-19T15:51:09Z","preferredFilename":"changeFloorClassifier 28"}